helixnet/__init__.py
helixnet/activations.py
helixnet/io.py
helixnet/layers.py
helixnet/loss.py
helixnet/metrics.py
helixnet/models.py
helixnet/optimizers.py
helixnet/preprocessing.py
helixnet-0.6.1.dist-info/METADATA
helixnet-0.6.1.dist-info/WHEEL
helixnet-0.6.1.dist-info/licenses/LICENSE
helixnet-0.6.1.dist-info/RECORD
