Metadata-Version: 2.4
Name: HelixNet
Version: 0.6.1
Summary: A powerful simple Neural Network building blocks based on MyGrad
Author: Amr Fahmy
License-Expression: MIT
License-File: LICENSE
Classifier: License :: OSI Approved :: MIT License
Classifier: Operating System :: OS Independent
Classifier: Programming Language :: Python :: 3
Classifier: Topic :: Scientific/Engineering :: Artificial Intelligence
Requires-Python: >=3.9
Requires-Dist: mygrad
Requires-Dist: numpy
Requires-Dist: rich
Provides-Extra: docs
Requires-Dist: sphinx; extra == 'docs'
Requires-Dist: sphinx-book-theme; extra == 'docs'
